ooop_wst.py
setup.py
ooop_wst.egg-info/PKG-INFO
ooop_wst.egg-info/SOURCES.txt
ooop_wst.egg-info/dependency_links.txt
ooop_wst.egg-info/requires.txt
ooop_wst.egg-info/top_level.txt